pyopenjtalk/__init__.py
pyopenjtalk/htsengine.cpython-310-x86_64-linux-gnu.so
pyopenjtalk/openjtalk.cpython-310-x86_64-linux-gnu.so
pyopenjtalk/utils.py
pyopenjtalk/version.py
pyopenjtalk/htsvoice/LICENSE_mei_normal.htsvoice
pyopenjtalk/htsvoice/README.md
pyopenjtalk/htsvoice/mei_normal.htsvoice
pyopenjtalk/open_jtalk_dic_utf_8-1.11/COPYING
pyopenjtalk/open_jtalk_dic_utf_8-1.11/char.bin
pyopenjtalk/open_jtalk_dic_utf_8-1.11/left-id.def
pyopenjtalk/open_jtalk_dic_utf_8-1.11/matrix.bin
pyopenjtalk/open_jtalk_dic_utf_8-1.11/pos-id.def
pyopenjtalk/open_jtalk_dic_utf_8-1.11/rewrite.def
pyopenjtalk/open_jtalk_dic_utf_8-1.11/right-id.def
pyopenjtalk/open_jtalk_dic_utf_8-1.11/sys.dic
pyopenjtalk/open_jtalk_dic_utf_8-1.11/unk.dic
openjtalk-0.3.0.dev3.dist-info/LICENSE.md
openjtalk-0.3.0.dev3.dist-info/METADATA
openjtalk-0.3.0.dev3.dist-info/WHEEL
openjtalk-0.3.0.dev3.dist-info/top_level.txt
openjtalk-0.3.0.dev3.dist-info/RECORD
